user_info_checker/__init__.py
user_info_checker/ip_master.py
user_info_checker/output_decorator.py
user_info_checker/system_info_checker.py
userinfochecker-0.0.3.dist-info/LICENSE
userinfochecker-0.0.3.dist-info/METADATA
userinfochecker-0.0.3.dist-info/WHEEL
userinfochecker-0.0.3.dist-info/top_level.txt
userinfochecker-0.0.3.dist-info/RECORD
